materialxgltf/__init__.py
materialxgltf/__main__.py
materialxgltf/core.py
materialxgltf/globals.py
materialxgltf/gltf2Mtlx.py
materialxgltf/mtlx2gltf.py
materialxgltf/data/BoomBoxWithAxes.gltf
materialxgltf/data/BoomBoxWithAxes.mtlx
materialxgltf/data/BoomBoxWithAxes.mtlx.glb
materialxgltf/data/BoomBoxWithAxes.mtlx.gltf
materialxgltf/data/BoomBoxWithAxes_baseColor.png
materialxgltf/data/BoomBoxWithAxes_baseColor1.png
materialxgltf/data/BoomBoxWithAxes_emissive.png
materialxgltf/data/BoomBoxWithAxes_normal.png
materialxgltf/data/BoomBoxWithAxes_roughnessMetallic.png
materialxgltf/data/Marble_3D_gltf_pbr_base_color.png
materialxgltf/data/README.md
materialxgltf/data/README.pdf
materialxgltf/data/gltf_test_nondefault_pbr.mtlx
materialxgltf/data/gltf_test_nondefault_pbr.mtlx.glb
materialxgltf/data/gltf_test_nondefault_pbr.mtlx.gltf
materialxgltf/data/shaderball.gltf
materialxgltf/data/shaderball_data.bin
materialxgltf/data/standard_surface_marble_solid.mtlx
materialxgltf/data/standard_surface_marble_solid.mtlx.glb
materialxgltf/data/standard_surface_marble_solid.mtlx.gltf
materialxgltf/data/standard_surface_marble_solid.mtlx_baked.mtlx
materialxgltf-1.39.4.dist-info/LICENSE
materialxgltf-1.39.4.dist-info/METADATA
materialxgltf-1.39.4.dist-info/WHEEL
materialxgltf-1.39.4.dist-info/entry_points.txt
materialxgltf-1.39.4.dist-info/top_level.txt
materialxgltf-1.39.4.dist-info/RECORD
