Metadata-Version: 2.1
Name: materialxgltf
Version: 1.39.4
Summary: Bidirectional conversion utilities for MaterialX and glTF
Author-email: Bernard Kwok <kwokcb@gmail.com>
License: MIT License
Project-URL: Homepage, https://kwokcb.github.io/materialxgltf/
Project-URL: Issues, https://github.com/kwokcb/materialxgltf/issues
Project-URL: Source Code, https://github.com/kwokcb/materialxgltf
Project-URL: Documentation, https://kwokcb.github.io/materialxgltf/
Classifier: Intended Audience :: Developers
Classifier: Programming Language :: Python :: 3
Classifier: License :: OSI Approved :: MIT License
Classifier: Operating System :: OS Independent
Classifier: Topic :: Software Development :: Libraries :: Python Modules
Requires-Python: >=3.8
License-File: LICENSE
Requires-Dist: materialx==1.39.4
Requires-Dist: pygltflib
Provides-Extra: dev
Requires-Dist: jupyter; extra == "dev"
Requires-Dist: pytest; extra == "dev"
Requires-Dist: sphinx; extra == "dev"
